sailthru/__init__.py
sailthru/sailthru_client.py
sailthru/sailthru_error.py
sailthru/sailthru_http.py
sailthru/sailthru_response.py
sailthru_client-2.2.1.dist-info/DESCRIPTION.rst
sailthru_client-2.2.1.dist-info/METADATA
sailthru_client-2.2.1.dist-info/metadata.json
sailthru_client-2.2.1.dist-info/RECORD
sailthru_client-2.2.1.dist-info/top_level.txt
sailthru_client-2.2.1.dist-info/WHEEL
sailthru_client-2.2.1.dist-info/zip-safe
