Metadata-Version: 2.0
Name: sailthru-client
Version: 2.2.1
Summary: Python client for Sailthru API
Home-page: https://github.com/sailthru/sailthru-python-client
Author: Sailthru Inc.
Author-email: support@sailthru.com
License: MIT License
Keywords: sailthru api
Platform: UNKNOWN
Classifier: License :: OSI Approved :: MIT License
Classifier: Topic :: Utilities
Classifier: Programming Language :: Python
Classifier: Programming Language :: Python :: 3
Classifier: Operating System :: OS Independent
Classifier: Natural Language :: English
Requires-Dist: requests (>=2.6.0)
Requires-Dist: simplejson (>=3.0.7)
